setup.py
SIMISToolBox.egg-info/PKG-INFO
SIMISToolBox.egg-info/SOURCES.txt
SIMISToolBox.egg-info/dependency_links.txt
SIMISToolBox.egg-info/requires.txt
SIMISToolBox.egg-info/top_level.txt
SIMSIToolBox/__init__.py