Metadata-Version: 1.1
Name: SIMISToolBox
Version: 0.0.1
Summary: Functions for analysis of stable isotope labeling mass spectrometry imaging data
Home-page: https://github.com/e-stan/imaging/
Author: Ethan Stancliffe
Author-email: estancl1234@gmail.com
License: MIT
Download-URL: https://github.com/e-stan/imaging/archive/v0.0.1.tar.gz
Keywords: Metabolomics,Mass Spectrometry Imaging,Stable Isotope Labeling
Platform: UNKNOWN
Classifier: Development Status :: 3 - Alpha
Classifier: Intended Audience :: Developers
Classifier: Topic :: Software Development :: Build Tools
Classifier: License :: OSI Approved :: MIT License
Classifier: Programming Language :: Python :: 3.7
